{
  "folder": "kHSYUTn6UUJsIu4l",
  "name": "Disfiguring Scar (Stabilized)",
  "type": "criticalWound",
  "img": "icons/svg/item-bag.svg",
  "system": {
    "htmlFields": [
      "description"
    ],
    "description": "",
    "criticalLevel": "simple",
    "treatment": "stabilized",
    "location": "head",
    "daysHealed": 0,
    "healingTime": 0,
    "sterilized": false,
    "followUp": "Compendium.TheWitcherTRPG.criticalWounds.Item.kbeASc2PnnkYc5SR",
    "lesserEffect": true
  },
  "effects": [
    {
      "type": "base",
      "name": "Disfiguring Scar (Stabilized)",
      "origin": "Compendium.TheWitcherTRPG.criticalWounds.Item.AJeuZeFF29nEI5fc",
      "duration": {
        "startTime": null,
        "combat": null,
        "seconds": null,
        "rounds": null,
        "turns": null,
        "startRound": null,
        "startTurn": null
      },
      "disabled": false,
      "img": "icons/svg/item-bag.svg",
      "_id": "y90olXT4UlLCn0pJ",
      "system": {
        "applySelf": false,
        "applyOnTarget": false,
        "applyOnHit": false,
        "applyOnDamage": false
      },
      "changes": [
        {
          "key": "system.skills.emp.charisma.activeEffectModifiers",
          "mode": 2,
          "value": "-1",
          "priority": null
        },
        {
          "key": "system.skills.emp.persuasion.activeEffectModifiers",
          "mode": 2,
          "value": "-1",
          "priority": null
        },
        {
          "key": "system.skills.emp.seduction.activeEffectModifiers",
          "mode": 2,
          "value": "-1",
          "priority": null
        },
        {
          "key": "system.skills.emp.leadership.activeEffectModifiers",
          "mode": 2,
          "value": "-1",
          "priority": null
        },
        {
          "key": "system.skills.emp.deceit.activeEffectModifiers",
          "mode": 2,
          "value": "-1",
          "priority": null
        },
        {
          "key": "system.skills.int.socialetq.activeEffectModifiers",
          "mode": 2,
          "value": "-1",
          "priority": null
        }
      ],
      "description": "",
      "tint": "#ffffff",
      "transfer": true,
      "statuses": [],
      "sort": 0,
      "flags": {
        "statuscounter": {
          "value": 1,
          "config": {
            "type": "default"
          },
          "visible": false
        }
      },
      "_stats": {
        "compendiumSource": null,
        "duplicateSource": null,
        "exportSource": null,
        "coreVersion": "13.351",
        "systemId": "TheWitcherTRPG",
        "systemVersion": "AUTOMATICALLY REPLACED BY GITHUB WORKFLOW ACTION"
      },
      "_key": "!items.effects!AJeuZeFF29nEI5fc.y90olXT4UlLCn0pJ"
    }
  ],
  "flags": {},
  "_stats": {
    "compendiumSource": null,
    "duplicateSource": null,
    "exportSource": null,
    "coreVersion": "13.351",
    "systemId": "TheWitcherTRPG",
    "systemVersion": "AUTOMATICALLY REPLACED BY GITHUB WORKFLOW ACTION"
  },
  "_id": "AJeuZeFF29nEI5fc",
  "ownership": {
    "default": 0,
    "ugXtPMJIktbl63QV": 3
  },
  "sort": 800000,
  "_key": "!items!AJeuZeFF29nEI5fc"
}
